[{"id":"c265a2c5.9c9c","type":"tab","label":"Flow 5","disabled":false,"info":""},{"id":"2469166.78b8dea","type":"ui_form","z":"c265a2c5.9c9c","name":"","label":"","group":"18aab0f2.a1ab3f","order":7,"width":0,"height":0,"options":[{"label":"Hello. What would you like to say?","value":"text","type":"text","required":true,"rows":null}],"formValue":{"text":""},"payload":"","submit":"submit","cancel":"cancel","topic":"","x":130,"y":220,"wires":[["6cb0eca.1eee514"]]},{"id":"6cb0eca.1eee514","type":"function","z":"c265a2c5.9c9c","name":"","func":"msg.payload=msg.payload.text;\nreturn msg;","outputs":1,"noerr":0,"initialize":"","finalize":"","x":290,"y":160,"wires":[["3d706dd2.22e7f2"]]},{"id":"901084b2.db4ba8","type":"function","z":"c265a2c5.9c9c","name":"","func":"msg.payload=msg.payload.output.text[0];\nreturn msg;","outputs":1,"noerr":0,"initialize":"","finalize":"","x":540,"y":200,"wires":[["5a62e43d.805d3c"]]},{"id":"3d706dd2.22e7f2","type":"watson-conversation-v1","z":"c265a2c5.9c9c","name":"","workspaceid":"fdee9aa7-1f4d-48b8-82d0-f988a83b1811","multiuser":false,"context":true,"empty-payload":false,"service-endpoint":"https://api.eu-gb.assistant.watson.cloud.ibm.com/instances/0687bdd7-d7a1-474b-983c-358308addf5b","timeout":"","optout-learning":false,"x":450,"y":100,"wires":[["e6d8d462.17fa98","901084b2.db4ba8"]]},{"id":"e6d8d462.17fa98","type":"debug","z":"c265a2c5.9c9c","name":"","active":false,"tosidebar":true,"console":false,"tostatus":false,"complete":"payload","targetType":"msg","statusVal":"","statusType":"auto","x":700,"y":100,"wires":[]},{"id":"5a62e43d.805d3c","type":"ui_text","z":"c265a2c5.9c9c","group":"18aab0f2.a1ab3f","order":9,"width":"5","height":"5","name":"","label":"Bot","format":"{{msg.payload}}","layout":"col-center","x":690,"y":260,"wires":[]},{"id":"18aab0f2.a1ab3f","type":"ui_group","z":"","name":"Shopping chatbot","tab":"3c4c92b8.7be20e","order":1,"disp":true,"width":"6","collapse":false},{"id":"3c4c92b8.7be20e","type":"ui_tab","z":"","name":"Welcome","icon":"dashboard","disabled":false,"hidden":false}]